pinion/__init__.py
pinion/cli.py
pinion/errors.py
pinion/inmemory.py
pinion/queue.py
pinion/registry.py
pinion/retry.py
pinion/sqlite_storage.py
pinion/storage.py
pinion/types.py
pinion/worker.py
pinion/py.typed
pinion_queue-0.2.7.dist-info/METADATA
pinion_queue-0.2.7.dist-info/WHEEL
pinion_queue-0.2.7.dist-info/entry_points.txt
pinion_queue-0.2.7.dist-info/licenses/LICENSE
pinion_queue-0.2.7.dist-info/RECORD
