Metadata-Version: 2.4
Name: pinion-queue
Version: 0.2.7
Summary: Pinion: a tiny pluggable job queue with retries.
Project-URL: Homepage, https://github.com/Nouman64-cat/Pinion
Project-URL: Issues, https://github.com/Nouman64-cat/Pinion/issues
Author-email: Nouman Ejaz <working.nouman.ejaz@gmail.com>
License: MIT
License-File: LICENSE
Classifier: License :: OSI Approved :: MIT License
Classifier: Operating System :: OS Independent
Classifier: Programming Language :: Python :: 3
Classifier: Topic :: System :: Distributed Computing
Classifier: Typing :: Typed
Requires-Python: >=3.12
